krl_network/__init__.py
krl_network/__version__.py
krl_network/community/__init__.py
krl_network/community/dynamics.py
krl_network/community/hierarchical.py
krl_network/community/label_propagation.py
krl_network/community/modularity.py
krl_network/community/overlapping.py
krl_network/community/spectral.py
krl_network/core/__init__.py
krl_network/core/base.py
krl_network/core/exceptions.py
krl_network/core/result.py
krl_network/metrics/__init__.py
krl_network/metrics/centrality.py
krl_network/metrics/clustering.py
krl_network/metrics/path_analysis.py
krl_network/metrics/statistics.py
krl_network/networks/__init__.py
krl_network/networks/base_economic.py
krl_network/networks/input_output.py
krl_network/networks/regional.py
krl_network/networks/supply_chain.py
krl_network/networks/trade.py
krl_network/utils/__init__.py
krl_network/utils/converters.py
krl_network/utils/io.py
krl_network/utils/validation.py
krl_network_analysis-0.2.0.dist-info/licenses/LICENSE
krl_network_analysis-0.2.0.dist-info/METADATA
krl_network_analysis-0.2.0.dist-info/WHEEL
krl_network_analysis-0.2.0.dist-info/entry_points.txt
krl_network_analysis-0.2.0.dist-info/top_level.txt
krl_network_analysis-0.2.0.dist-info/RECORD
