Metadata-Version: 2.4
Name: krl-network-analysis
Version: 0.2.0
Summary: Economic network analysis tools for the Khipu Intelligence Suite
Author-email: KR-Labs Foundation <dev@krlabs.org>
Maintainer-email: KR-Labs Foundation <support@krlabs.dev>
License: Apache-2.0
Project-URL: Homepage, https://krlabs.dev
Project-URL: Documentation, https://docs.krlabs.dev/network-analysis
Project-URL: Repository, https://github.com/kr-labs/krl-network-analysis
Project-URL: Changelog, https://github.com/kr-labs/krl-network-analysis/blob/main/CHANGELOG.md
Classifier: Development Status :: 3 - Alpha
Classifier: Intended Audience :: Science/Research
Classifier: License :: OSI Approved :: Apache Software License
Classifier: Programming Language :: Python :: 3
Classifier: Programming Language :: Python :: 3.11
Requires-Python: >=3.11
License-File: LICENSE
Requires-Dist: networkx>=3.2.0
Requires-Dist: pandas>=2.1.0
Requires-Dist: numpy>=1.26.0
Requires-Dist: scipy>=1.11.0
Requires-Dist: krl-open-core>=0.2.0
Requires-Dist: krl-types~=0.2.0
Provides-Extra: dev
Requires-Dist: black>=23.0.0; extra == "dev"
Requires-Dist: isort>=5.12.0; extra == "dev"
Requires-Dist: flake8>=6.0.0; extra == "dev"
Requires-Dist: mypy>=1.5.0; extra == "dev"
Provides-Extra: test
Requires-Dist: pytest>=7.4.0; extra == "test"
Requires-Dist: pytest-cov>=4.1.0; extra == "test"
Requires-Dist: pytest-mock>=3.11.0; extra == "test"
Provides-Extra: visualization
Requires-Dist: plotly>=5.17.0; extra == "visualization"
Requires-Dist: pyvis>=0.3.0; extra == "visualization"
Requires-Dist: matplotlib>=3.7.0; extra == "visualization"
Provides-Extra: performance
Requires-Dist: python-igraph>=0.10.0; extra == "performance"
Requires-Dist: graph-tool>=2.45; extra == "performance"
Dynamic: license-file
